.gitignore
.hgignore
MANIFEST.in
command_line.txt
concepts.txt
config.txt
dependencies.txt
file_searching_algorithm.txt
implicit_rules.txt
index.htm
license.txt
main_features.txt
markdown_scoped_links.txt
markdown_scoped_links_notes.txt
markdown_syntax.txt
markdown_tutorial.txt
math_syntax.txt
option_files.txt
pattern_matching.txt
problem.txt
release_history.txt
remark.py
remark.txt
remark_config.json
remark_license.txt
remark_syntax.txt
setup.py
style.txt
tags.txt
understanding.txt
user_documentation.txt
variables.txt
variables_as_storage.txt
variables_as_transforms.txt
warnings.txt
.git/COMMIT_EDITMSG
.git/FETCH_HEAD
.git/HEAD
.git/config
.git/description
.git/index
.git/packed-refs
.git/hooks/applypatch-msg.sample
.git/hooks/commit-msg.sample
.git/hooks/fsmonitor-watchman.sample
.git/hooks/post-update.sample
.git/hooks/pre-applypatch.sample
.git/hooks/pre-commit.sample
.git/hooks/pre-merge-commit.sample
.git/hooks/pre-push.sample
.git/hooks/pre-rebase.sample
.git/hooks/pre-receive.sample
.git/hooks/prepare-commit-msg.sample
.git/hooks/update.sample
.git/info/exclude
.git/logs/HEAD
.git/logs/refs/heads/master
.git/logs/refs/remotes/origin/HEAD
.git/logs/refs/remotes/origin/master
.git/objects/0b/21c67e055f6106d4bfe2e9fc0f31635ad44ddd
.git/objects/18/862f30f7d962b1fbeb5069220aa5ad72f1b71f
.git/objects/1f/fd681e4502097c888f29c3129e035a797e1d21
.git/objects/2c/03ac84e54f5ef235211be8a595eb57d5aafe0f
.git/objects/32/0c59c21d0a40f71ef019344d5b85cd3d3324e7
.git/objects/35/51aed6409dc7982f5825ff5aa95612d0d27f99
.git/objects/39/3ebd8354c467d17558f29c4596abf17f374e74
.git/objects/3a/b265a7a68cf9a1634c940b40bc957a12c06e2a
.git/objects/42/a0f91f1f6da49f09dcdfa272542c63c87932e0
.git/objects/44/53aa917b7d699739006aa3afa8af83c455acab
.git/objects/46/4e9a106345d6c9550a4b13fe7811de5973770c
.git/objects/56/0039171dace35c555e20bf41330408deabea1f
.git/objects/65/7171eebe58fd229a083994bdb8ba61a88bf21e
.git/objects/67/b43f2b64a4608db80a916fd95494cb84739754
remark.egg-info/PKG-INFO
remark.egg-info/SOURCES.txt
remark.egg-info/dependency_links.txt
remark.egg-info/not-zip-safe
remark.egg-info/requires.txt
remark.egg-info/top_level.txt