Metadata-Version: 2.1
Name: remark
Version: 1.7.9
Summary: Generates html documentation for software libraries from lightweight markup.
Home-page: http://kaba.hilvi.org/remark
Author: Kalle Rutanen
Author-email: kaba@hilvi.org
License: MIT
Keywords: lightweight markup software documentation html
Classifier: Development Status :: 5 - Production/Stable
Classifier: License :: OSI Approved :: MIT License
Classifier: Programming Language :: Python :: 2
Classifier: Programming Language :: Python :: 3
Classifier: Environment :: Console
Classifier: Topic :: Software Development :: Documentation
Classifier: Intended Audience :: Developers
Classifier: Intended Audience :: Science/Research
Classifier: Operating System :: OS Independent
License-File: license.txt
